django_learngual-0.886.dist-info/licenses/LICENSE
learngual/__init__.py
learngual/admin.py
learngual/ai_sdk.py
learngual/apps.py
learngual/authentication.py
learngual/cache_models.py
learngual/custom_exceptions.py
learngual/custom_fields.py
learngual/db_helpers.py
learngual/decorators.py
learngual/enums.py
learngual/interface.py
learngual/kombu_patch.py
learngual/logger.py
learngual/logging.py
learngual/manager.py
learngual/middleware.py
learngual/models.py
learngual/permissions.py
learngual/pydantic_model.py
learngual/schema.py
learngual/service_requests.py
learngual/signals.py
learngual/transform_template.py
learngual/translator.py
learngual/urls.py
learngual/utils.py
learngual/management/__init_.py
learngual/management/__init__.py
learngual/management/commands/__init__.py
learngual/management/commands/download_email_template.py
learngual/management/commands/ensure_queue_priority.py
learngual/management/commands/prewarm_translation_cache.py
learngual/migrations/__init__.py
learngual/services/__init__.py
learngual/services/celery_beat_helper.py
learngual/settings/__init__.py
learngual/settings/base.py
learngual/settings/functions.py
learngual/settings/production.py
learngual/tests/__init__.py
learngual/tests/factories.py
learngual/tests/request_mock.py
learngual/tests/test_ai_sdk.py
learngual/tests/test_ai_sdk_qa.py
learngual/tests/test_authentication.py
learngual/tests/test_drf_endpoints.py
learngual/tests/test_utils.py
learngual/v1/__init__.py
learngual/v1/serializers.py
learngual/v1/urls.py
learngual/v1/views.py
django_learngual-0.886.dist-info/METADATA
django_learngual-0.886.dist-info/WHEEL
django_learngual-0.886.dist-info/top_level.txt
django_learngual-0.886.dist-info/RECORD
