Metadata-Version: 2.4
Name: django-learngual
Version: 0.886
Summary: Learngual helper package
Home-page: https://learngual.com
Author: learngual
Author-email: developer@learngual.com
Maintainer: Aniekutmfon
Maintainer-email: aniekutmfonekere@gmail.com
License: Proprietary Software License Agreement
Classifier: Environment :: Web Environment
Classifier: Framework :: Django
Classifier: Intended Audience :: Developers
Classifier: License :: OSI Approved :: MIT License
Classifier: Operating System :: OS Independent
Classifier: Programming Language :: Python :: 3
Classifier: Programming Language :: Python :: 3 :: Only
Classifier: Programming Language :: Python :: 3.5
Classifier: Programming Language :: Python :: 3.6
Classifier: Programming Language :: Python :: 3.7
Classifier: Programming Language :: Python :: 3.8
Classifier: Programming Language :: Python :: 3.9
Classifier: Programming Language :: Python :: 3.10
Classifier: Topic :: Software Development :: Libraries :: Python Modules
License-File: LICENSE
Requires-Dist: gspread==6.1.2
Requires-Dist: django==4.0.8
Requires-Dist: GitPython==3.1.43
Requires-Dist: djangorestframework-simplejwt==4.8.0
Requires-Dist: Faker==16.1.0
Requires-Dist: pydantic[email]==2.11.0
Requires-Dist: pydantic_core==2.33.0
Requires-Dist: djangorestframework==3.14.0
Requires-Dist: django-filter==23.2
Requires-Dist: django-environ==0.12.0
Requires-Dist: python-json-logger==3.2.1
Requires-Dist: sentry-sdk[celery,django]==1.45.0
Dynamic: license-file
